<?xml version="1.0"?>
<game_state>
	<input />
	<window />
	<textures />
	<fonts />
	<audio />
	<map />
	<scene sceneNumber="2" />
	<:anonymous />
	<entity_manager>
		<entity type="player" x="836" y="1841" />
		<entity type="coin" x="1032" y="172" />
		<entity type="coin" x="1118" y="172" />
		<entity type="coin" x="1548" y="344" />
		<entity type="coin" x="1634" y="1462" />
		<entity type="coin" x="1720" y="1634" />
		<entity type="coin" x="1806" y="1376" />
		<entity type="coin" x="1892" y="1548" />
		<entity type="coin" x="1978" y="516" />
		<entity type="coin" x="2408" y="774" />
		<entity type="coin" x="2666" y="1978" />
		<entity type="coin" x="2752" y="516" />
		<entity type="coin" x="2838" y="516" />
		<entity type="coin" x="3268" y="774" />
		<entity type="coin" x="3354" y="774" />
		<entity type="coin" x="3440" y="1892" />
		<entity type="coin" x="3526" y="430" />
		<entity type="coin" x="4214" y="1548" />
		<entity type="coin" x="4902" y="1032" />
		<entity type="coin" x="4902" y="1118" />
		<entity type="coin" x="4902" y="1204" />
		<entity type="coin" x="4988" y="1032" />
		<entity type="coin" x="4988" y="1204" />
		<entity type="coin" x="5074" y="1032" />
		<entity type="coin" x="5074" y="1204" />
		<entity type="coin" x="5160" y="1032" />
		<entity type="coin" x="5160" y="1118" />
		<entity type="coin" x="5160" y="1204" />
		<entity type="coin" x="5160" y="1892" />
		<entity type="coin" x="6020" y="344" />
		<entity type="coin" x="6020" y="860" />
		<entity type="coin" x="6020" y="1376" />
		<entity type="coin" x="6278" y="172" />
		<entity type="coin" x="6278" y="602" />
	</entity_manager>
	<gui>
		<gui_counter type="coins" value="1" />
		<gui_counter type="lifes" value="7" />
		<gui_counter type="score" value="165" />
	</gui>
	<colliders />
	<:anonymous />
	<pathfinding />
	<renderer>
		<camera x="0" y="-1373" />
	</renderer>
</game_state>
